PyShorts/__init__.py
PyShorts/funcs.py
PyShorts/non_use_funcs.py
PyShorts/Sub_Functions/__init__.py
PyShorts/Sub_Functions/funcs.py
PyShorts/Sub_Functions/non_use_funcs.py
PyShortsByAbdus-0.6.dist-info/METADATA
PyShortsByAbdus-0.6.dist-info/WHEEL
PyShortsByAbdus-0.6.dist-info/top_level.txt
PyShortsByAbdus-0.6.dist-info/RECORD
