Metadata-Version: 2.1
Name: PyShortsByAbdus
Version: 0.6
Summary: In summary, PyShorts is a game-changing Python package that empowers developers to write code swiftly and efficiently. By providing shorthand functions, code snippets, intelligent code completion, and code generation capabilities, PyShorts streamlines the coding process, enabling developers to accelerate their productivity and deliver high-quality code with ease.
Author: Abdus-Samad
Author-email: Samadgame0910@gmail.com
Requires-Dist: Functions
Requires-Dist: pillow
Requires-Dist: setuptools
Requires-Dist: requests
